red_overlay/__init__.py
red_overlay/red_overlay.py
red_overlay-1.0.2.dist-info/METADATA
red_overlay-1.0.2.dist-info/WHEEL
red_overlay-1.0.2.dist-info/licenses/LICENSE
red_overlay-1.0.2.dist-info/RECORD
